flask_queue_sse/__init__.py
flask_queue_sse-0.1.3.dist-info/LICENSE.md
flask_queue_sse-0.1.3.dist-info/WHEEL
flask_queue_sse-0.1.3.dist-info/METADATA
flask_queue_sse-0.1.3.dist-info/RECORD
